asgebsmanager
