Metadata-Version: 2.1
Name: asgebsmanager
Version: 1.5.3
Summary: AWS Asg ebs manager
Author: Raghav Gupta
Classifier: Programming Language :: Python :: 3
Requires-Dist: boto3
Requires-Dist: botocore
Requires-Dist: certifi
Requires-Dist: charset-normalizer
Requires-Dist: idna
Requires-Dist: jmespath
Requires-Dist: python-dateutil
Requires-Dist: requests
Requires-Dist: s3transfer
Requires-Dist: six
Requires-Dist: urllib3
